{
  "metas": [
    {
        "id": "almalusa",
        "name": "Alma Lusa",
        "year": 2025,
        "poster": "https://sp.jdinformatica.com/stremio/icons/almalusa.png",
        "posterShape": "regular",
        "banner": "https://sp.jdinformatica.com/stremio/icons/almalusa.png",
        "isFree": true,
        "type": "movie"
    },
    {
        "id": "cmcmusic",
        "name": "CMC California music",
        "year": 2025,
        "poster": "https://sp.jdinformatica.com/stremio/icons/cmcmusic.png",
        "posterShape": "regular",
        "banner": "https://sp.jdinformatica.com/stremio/icons/cmcmusic.png",
        "isFree": true,
        "type": "movie"
    },
    {
        "id": "solmusica",
        "name": "Sol Musica",
        "year": 2025,
        "poster": "https://sp.jdinformatica.com/stremio/icons/solmusica.png",
        "posterShape": "regular",
        "banner": "https://sp.jdinformatica.com/stremio/icons/solmusica.png",
        "isFree": true,
        "type": "movie"
    },
	{
      "id": "lovesongs",
       "name": "Love Songs",
        "year": 2025,
        "poster": "https://sp.jdinformatica.com/stremio/icons/lovesongs.png",
        "posterShape": "regular",
        "banner": "https://sp.jdinformatica.com/stremio/icons/lovesongs.png",
        "isFree": true,
        "type": "movie"
    },
	{
      "id": "vevo",
       "name": "VEVO Music",
        "year": 2025,
        "poster": "https://sp.jdinformatica.com/stremio/icons/vevo.png",
        "posterShape": "regular",
        "banner": "https://sp.jdinformatica.com/stremio/icons/vevo.png",
        "isFree": true,
        "type": "movie"
    },
    {
        "id": "assimeportugal",
        "name": "Assim é Portugal",
        "year": 2025,
        "poster": "https://sp.jdinformatica.com/stremio/icons/assimeportugal.png",
        "posterShape": "regular",
        "banner": "https://sp.jdinformatica.com/stremio/icons/assimeportugal.png",
        "isFree": true,
        "type": "movie"
    }
  ]
}
